Metadata-Version: 2.4
Name: sopel-http
Version: 0.1.1
Summary: An HTTP server for the Sopel IRC bot framework
Author-email: Trevor Bergeron <mal@sec.gd>
Project-URL: HomePage, https://github.com/half-duplex/sopel-http
Keywords: irc,sopel
Classifier: Development Status :: 4 - Beta
Classifier: Intended Audience :: Developers
Classifier: Intended Audience :: System Administrators
Classifier: License :: OSI Approved :: European Union Public Licence 1.2 (EUPL 1.2)
Classifier: Operating System :: OS Independent
Classifier: Topic :: Communications :: Chat :: Internet Relay Chat
Requires-Python: ~=3.9
License-File: LICENSE.txt
Requires-Dist: sopel~=7.1.9
Requires-Dist: Flask~=2.1.2
Requires-Dist: gevent~=25.5.1
Dynamic: license-file
